grafico_fit/__init__.py
grafico_fit/funzioniFit.py
grafico_fit-1.8.0.dist-info/LICENSE.txt
grafico_fit-1.8.0.dist-info/METADATA
grafico_fit-1.8.0.dist-info/WHEEL
grafico_fit-1.8.0.dist-info/top_level.txt
grafico_fit-1.8.0.dist-info/RECORD
