Metadata-Version: 2.1
Name: grafico-fit
Version: 1.8.0
Summary: Package per generare grafici di fit partendo da dati in fogli Excel
Home-page: https://gitlab.com/cremo_sns/json_fit.git
Author: Luca Cremonesi
Author-email: luca.cremonesi@sns.it
Project-URL: Bug Tracker, https://gitlab.com/cremo_sns/json_fit/-/issues
Classifier: Programming Language :: Python :: 3
Classifier: License :: OSI Approved :: MIT License
Classifier: Operating System :: OS Independent
Requires-Python: >=3.6
License-File: LICENSE.txt
Requires-Dist: numpy
Requires-Dist: matplotlib
Requires-Dist: scipy
Requires-Dist: pandas
Requires-Dist: openpyxl
Requires-Dist: pint
